[
  {
    "model": "courses.course",
    "pk": 1,
    "fields": {
      "title": "Code-testing",
      "preview": "",
      "description": "Code testing base skills"
    }
  },
  {
    "model": "courses.lesson",
    "pk": 1,
    "fields": {
      "course": 1,
      "title": "Code-testing base rules",
      "description": "Start your learning here",
      "preview": "",
      "video_url": null
    }
  },
  {
    "model": "courses.payment",
    "pk": 1,
    "fields": {
      "user": 1,
      "payment_date": "2023-08-06",
      "course": 1,
      "lesson": 1,
      "payment_summ": 20000,
      "payment_type": "наличные"
    }
  },
  {
    "model": "courses.payment",
    "pk": 2,
    "fields": {
      "user": 1,
      "payment_date": "2023-08-06",
      "course": 1,
      "lesson": 1,
      "payment_summ": 25000,
      "payment_type": "перевод"
    }
  },
  {
    "model": "courses.payment",
    "pk": 3,
    "fields": {
      "user": 1,
      "payment_date": "2023-08-06",
      "course": 1,
      "lesson": 1,
      "payment_summ": 30000,
      "payment_type": "наличные"
    }
  }
]